expectra/__init__.py
expectra/exafs.py
expectra/feff
expectra/feff.py
expectra/fft.py
expectra/io.py
expectra-1.0.5.data/scripts/expectra
expectra-1.0.5.data/scripts/feff
expectra-1.0.5.data/scripts/harmonic-sampler
expectra-1.0.5.data/scripts/pdfstats
expectra-1.0.5.data/scripts/xafsft
expectra-1.0.5.dist-info/LICENSE.txt
expectra-1.0.5.dist-info/METADATA
expectra-1.0.5.dist-info/WHEEL
expectra-1.0.5.dist-info/top_level.txt
expectra-1.0.5.dist-info/RECORD
