Metadata-Version: 2.1
Name: expectra
Version: 1.0.5
Summary: Code for simulating EXAFS calculations from molecular dynamics trajectories or normal modes using FEFF
Home-page: https://github.com/SamChill/expectra
Author: Samuel T. Chill
Author-email: samchill@gmail.com
License: LICENSE.txt
License-File: LICENSE.txt
Requires-Dist: numpy (>=1.5.0)
Requires-Dist: mpi4py (>=1.3)
Requires-Dist: ase (>=3.11.0)
